backup/__init__.py
backup/base.py
backup/dump.py
backup/load.py
mongo/__init__.py
mongo/abstract.py
mongo/elastic2mongo/__init__.py
mongo/elastic2mongo/base_streamer.py
mongo/elastic2mongo/data_streamer.py
mongo/elastic2mongo/elastic2mongo.py
mongo/elastic2mongo/update_streamer.py
mongo/mongo2elastic/__init__.py
mongo/mongo2elastic/base_streamer.py
mongo/mongo2elastic/data_streamer.py
mongo/mongo2elastic/mongo2elastic.py
mongo/mongo2elastic/update_streamer.py
elastic_tools-1.0.3.dist-info/METADATA
elastic_tools-1.0.3.dist-info/WHEEL
elastic_tools-1.0.3.dist-info/entry_points.txt
elastic_tools-1.0.3.dist-info/top_level.txt
elastic_tools-1.0.3.dist-info/RECORD
