Metadata-Version: 2.1
Name: elastic-tools
Version: 1.0.3
Summary: UNKNOWN
Home-page: https://github.com/petricore-tech/elastictools.git
License: UNKNOWN
Platform: UNKNOWN
Requires-Dist: aiofiles (==0.6.0)
Requires-Dist: aiohttp (==3.7.4.post0)
Requires-Dist: astroid (==2.5.6)
Requires-Dist: async-timeout (==3.0.1)
Requires-Dist: attrs (==20.3.0)
Requires-Dist: bleach (==3.3.0)
Requires-Dist: build (==0.4.0)
Requires-Dist: certifi (==2020.12.5)
Requires-Dist: chardet (==4.0.0)
Requires-Dist: colorama (==0.4.4)
Requires-Dist: docutils (==0.17.1)
Requires-Dist: elastic-tools (==1.0.1)
Requires-Dist: elasticsearch (==7.12.1)
Requires-Dist: idna (==3.1)
Requires-Dist: importlib-metadata (==4.0.1)
Requires-Dist: isort (==5.8.0)
Requires-Dist: keyring (==23.0.1)
Requires-Dist: lazy-object-proxy (==1.6.0)
Requires-Dist: mccabe (==0.6.1)
Requires-Dist: motor (==2.4.0)
Requires-Dist: multidict (==5.1.0)
Requires-Dist: mypy-extensions (==0.4.3)
Requires-Dist: packaging (==20.9)
Requires-Dist: pep517 (==0.10.0)
Requires-Dist: pkginfo (==1.7.0)
Requires-Dist: Pygments (==2.9.0)
Requires-Dist: pylint (==2.8.2)
Requires-Dist: pymongo (==3.11.4)
Requires-Dist: pyparsing (==2.4.7)
Requires-Dist: readme-renderer (==29.0)
Requires-Dist: requests (==2.25.1)
Requires-Dist: requests-toolbelt (==0.9.1)
Requires-Dist: rfc3986 (==1.5.0)
Requires-Dist: six (==1.16.0)
Requires-Dist: toml (==0.10.2)
Requires-Dist: tqdm (==4.60.0)
Requires-Dist: twine (==3.4.1)
Requires-Dist: typed-ast (==1.4.3)
Requires-Dist: typing-extensions (==3.10.0.0)
Requires-Dist: ujson (==4.0.2)
Requires-Dist: urllib3 (==1.26.4)
Requires-Dist: webencodings (==0.5.1)
Requires-Dist: websockets (==9.0.2)
Requires-Dist: wrapt (==1.12.1)
Requires-Dist: yarl (==1.6.3)
Requires-Dist: zipp (==3.4.1)
